{
  "description": "",
  "composes": [
    "../../typography"
  ],
  "ns": "evergreen",
  "type": "ReactNode",
  "dependencies": {
    "npm": {
      "evergreen/TextInput": "latest"
    }
  },
  "name": "TextInput",
  "ports": {
    "input": {
      "required": {
        "type": "boolean",
        "name": "required",
        "required": false,
        "propType": "bool"
      },
      "disabled": {
        "type": "boolean",
        "name": "disabled",
        "default": false,
        "propType": "bool"
      },
      "isInvalid": {
        "type": "boolean",
        "name": "isInvalid",
        "default": false,
        "propType": "bool"
      },
      "spellCheck": {
        "type": "boolean",
        "name": "spellCheck",
        "default": true,
        "propType": "bool"
      },
      "placeholder": {
        "type": "string",
        "name": "placeholder",
        "required": false
      },
      "appearance": {
        "type": "string",
        "name": "appearance",
        "default": null
      },
      "width": {
        "type": "union",
        "name": "width",
        "default": 280
      },
      "theme": {
        "type": "object",
        "name": "theme",
        "required": true
      },
      "className": {
        "type": "string",
        "name": "className",
        "required": false
      },
      "height": {
        "name": "height",
        "default": 32
      }
    },
    "output": {
      "component": {
        "title": "TextInput",
        "type": "Component"
      }
    }
  }
}